{
  "description": "A/B/C test comparing skip connection strategies (400s runs on 4xA100)",
  "date": "2026-04-25",
  "configs": {
    "no_skip": {
      "SKIP_ENABLED": 0,
      "DENSE_SKIP": 0,
      "params": 35936344
    },
    "sparse": {
      "SKIP_ENABLED": 1,
      "DENSE_SKIP": 0,
      "params": 35941464
    },
    "dense": {
      "SKIP_ENABLED": 1,
      "DENSE_SKIP": 1,
      "params": 35967064
    }
  },
  "val_bpb": {
    "no_skip": {
      "0": 3.486,
      "50": 1.9757,
      "100": 1.6491,
      "150": 1.5054,
      "200": 1.4449,
      "250": 1.4061,
      "300": 1.3839,
      "350": 1.3667,
      "387": 1.3008,
      "386": 1.301,
      "375": 1.312,
      "400": 1.3514,
      "450": 1.3408,
      "500": 1.3336,
      "550": 1.3232,
      "600": 1.3134,
      "650": 1.3003,
      "700": 1.2885,
      "750": 1.2764,
      "800": 1.2669,
      "850": 1.2575,
      "900": 1.2485,
      "950": 1.2401,
      "1000": 1.2313,
      "1050": 1.2232,
      "1100": 1.2151,
      "1150": 1.2072,
      "1200": 1.1997,
      "1250": 1.1934,
      "1273": 1.1922
    },
    "sparse": {
      "0": 3.486,
      "50": 1.9765,
      "100": 1.6598,
      "150": 1.506,
      "200": 1.442,
      "250": 1.4093,
      "300": 1.383,
      "350": 1.365,
      "387": 1.3008,
      "386": 1.301,
      "375": 1.312,
      "400": 1.352,
      "450": 1.3402,
      "500": 1.3332,
      "550": 1.3247,
      "600": 1.3126,
      "650": 1.2992,
      "700": 1.2874,
      "750": 1.277,
      "800": 1.2663,
      "850": 1.2573,
      "900": 1.2484,
      "950": 1.2399,
      "1000": 1.2311,
      "1050": 1.2227,
      "1100": 1.2146,
      "1150": 1.2068,
      "1200": 1.1993,
      "1250": 1.1931,
      "1273": 1.1922,
      "1293": 1.1906
    },
    "dense": {
      "0": 3.486,
      "50": 1.987,
      "100": 1.6748,
      "150": 1.5143,
      "200": 1.4535,
      "250": 1.4133,
      "300": 1.3896,
      "350": 1.3681,
      "387": 1.3008,
      "386": 1.301,
      "375": 1.312,
      "400": 1.3553,
      "450": 1.3426,
      "500": 1.3354,
      "550": 1.3259,
      "600": 1.3128,
      "650": 1.2993,
      "700": 1.2861,
      "750": 1.275,
      "800": 1.2648,
      "850": 1.2549,
      "900": 1.2459,
      "950": 1.237,
      "1000": 1.228,
      "1050": 1.2196,
      "1100": 1.2111,
      "1150": 1.2033,
      "1200": 1.1963,
      "1250": 1.1922,
      "1273": 1.1922,
      "1293": 1.1906,
      "1256": 1.1922
    }
  },
  "efficiency": {
    "no_skip": {
      "50": 0.030206,
      "100": 0.006531,
      "150": 0.002876,
      "200": 0.001209,
      "250": 0.000776,
      "300": 0.000445,
      "350": 0.000344,
      "387": 0.00034,
      "386": 0.000328,
      "375": 0.000281,
      "400": 0.000306,
      "450": 0.000213,
      "500": 0.000143,
      "550": 0.000208,
      "600": 0.000197,
      "650": 0.000261,
      "700": 0.000237,
      "750": 0.000241,
      "800": 0.000191,
      "850": 0.000188,
      "900": 0.000179,
      "950": 0.000168,
      "1000": 0.000176,
      "1050": 0.000163,
      "1100": 0.000162,
      "1150": 0.000159,
      "1200": 0.000149,
      "1250": 0.000127,
      "1273": 5.4e-05
    },
    "sparse": {
      "50": 0.03019,
      "100": 0.006334,
      "150": 0.003076,
      "200": 0.00128,
      "250": 0.000653,
      "300": 0.000527,
      "350": 0.000361,
      "387": 0.00034,
      "386": 0.000328,
      "375": 0.000281,
      "400": 0.000259,
      "450": 0.000238,
      "500": 0.000138,
      "550": 0.000172,
      "600": 0.000241,
      "650": 0.000267,
      "700": 0.000237,
      "750": 0.000207,
      "800": 0.000215,
      "850": 0.00018,
      "900": 0.000178,
      "950": 0.00017,
      "1000": 0.000176,
      "1050": 0.000167,
      "1100": 0.000162,
      "1150": 0.000157,
      "1200": 0.000149,
      "1250": 0.000124,
      "1273": 5.4e-05,
      "1293": 6e-05
    },
    "dense": {
      "50": 0.029981,
      "100": 0.006243,
      "150": 0.00321,
      "200": 0.001215,
      "250": 0.000804,
      "300": 0.000475,
      "350": 0.00043,
      "387": 0.00034,
      "386": 0.000328,
      "375": 0.000281,
      "400": 0.000256,
      "450": 0.000254,
      "500": 0.000143,
      "550": 0.00019,
      "600": 0.000262,
      "650": 0.000271,
      "700": 0.000264,
      "750": 0.000222,
      "800": 0.000204,
      "850": 0.000196,
      "900": 0.000181,
      "950": 0.000178,
      "1000": 0.00018,
      "1050": 0.000168,
      "1100": 0.000168,
      "1150": 0.000157,
      "1200": 0.000139,
      "1250": 8.2e-05,
      "1273": 5.4e-05,
      "1293": 6e-05,
      "1256": 1e-05
    }
  },
  "grad_norms": {
    "no_skip": {
      "skip": {
        "final": 0.002,
        "peak": 0.01282,
        "retained_pct": 15.6,
        "final_step": 1250
      },
      "embedding": {
        "final": 0.02582,
        "peak": 0.38251,
        "retained_pct": 6.8,
        "final_step": 1250
      },
      "layer00/scale": {
        "final": 0.00406,
        "peak": 0.02317,
        "retained_pct": 17.5,
        "final_step": 1250
      },
      "layer00/attn": {
        "final": 0.00972,
        "peak": 0.25578,
        "retained_pct": 3.8,
        "final_step": 1250
      },
      "layer00/mlp": {
        "final": 0.01549,
        "peak": 0.34773,
        "retained_pct": 4.5,
        "final_step": 1250
      },
      "layer01/scale": {
        "final": 0.00291,
        "peak": 0.02113,
        "retained_pct": 13.7,
        "final_step": 1250
      },
      "layer01/attn": {
        "final": 0.00864,
        "peak": 0.15657,
        "retained_pct": 5.5,
        "final_step": 1250
      },
      "layer01/mlp": {
        "final": 0.0139,
        "peak": 0.15014,
        "retained_pct": 9.3,
        "final_step": 1250
      },
      "layer02/scale": {
        "final": 0.00263,
        "peak": 0.0225,
        "retained_pct": 11.7,
        "final_step": 1250
      },
      "layer02/attn": {
        "final": 0.00907,
        "peak": 0.16062,
        "retained_pct": 5.6,
        "final_step": 1250
      },
      "layer02/mlp": {
        "final": 0.01488,
        "peak": 0.16803,
        "retained_pct": 8.9,
        "final_step": 1250
      },
      "layer03/scale": {
        "final": 0.00256,
        "peak": 0.02257,
        "retained_pct": 11.4,
        "final_step": 1250
      },
      "layer03/attn": {
        "final": 0.00916,
        "peak": 0.13495,
        "retained_pct": 6.8,
        "final_step": 1250
      },
      "layer03/mlp": {
        "final": 0.01336,
        "peak": 0.13175,
        "retained_pct": 10.1,
        "final_step": 1250
      },
      "layer04/scale": {
        "final": 0.00213,
        "peak": 0.01437,
        "retained_pct": 14.8,
        "final_step": 1250
      },
      "layer04/attn": {
        "final": 0.01073,
        "peak": 0.06872,
        "retained_pct": 15.6,
        "final_step": 1250
      },
      "layer04/mlp": {
        "final": 0.01418,
        "peak": 0.10551,
        "retained_pct": 13.4,
        "final_step": 1250
      },
      "layer05/scale": {
        "final": 0.00205,
        "peak": 0.01307,
        "retained_pct": 15.7,
        "final_step": 1250
      },
      "layer05/attn": {
        "final": 0.00945,
        "peak": 0.04913,
        "retained_pct": 19.2,
        "final_step": 1250
      },
      "layer05/mlp": {
        "final": 0.01342,
        "peak": 0.07524,
        "retained_pct": 17.8,
        "final_step": 1250
      },
      "layer06/scale": {
        "final": 0.00222,
        "peak": 0.01714,
        "retained_pct": 13.0,
        "final_step": 1250
      },
      "layer06/attn": {
        "final": 0.01013,
        "peak": 0.06106,
        "retained_pct": 16.6,
        "final_step": 1250
      },
      "layer06/mlp": {
        "final": 0.01308,
        "peak": 0.07495,
        "retained_pct": 17.5,
        "final_step": 1250
      },
      "layer07/scale": {
        "final": 0.00285,
        "peak": 0.02111,
        "retained_pct": 13.5,
        "final_step": 1250
      },
      "layer07/attn": {
        "final": 0.01035,
        "peak": 0.0764,
        "retained_pct": 13.6,
        "final_step": 1250
      },
      "layer07/mlp": {
        "final": 0.01431,
        "peak": 0.08034,
        "retained_pct": 17.8,
        "final_step": 1250
      },
      "layer08/scale": {
        "final": 0.00326,
        "peak": 0.02429,
        "retained_pct": 13.4,
        "final_step": 1250
      },
      "layer08/attn": {
        "final": 0.01127,
        "peak": 0.11593,
        "retained_pct": 9.7,
        "final_step": 1250
      },
      "layer08/mlp": {
        "final": 0.01629,
        "peak": 0.10048,
        "retained_pct": 16.2,
        "final_step": 1250
      },
      "layer09/scale": {
        "final": 0.00422,
        "peak": 0.02575,
        "retained_pct": 16.4,
        "final_step": 1250
      },
      "layer09/attn": {
        "final": 0.01366,
        "peak": 0.16084,
        "retained_pct": 8.5,
        "final_step": 1250
      },
      "layer09/mlp": {
        "final": 0.01869,
        "peak": 0.12172,
        "retained_pct": 15.4,
        "final_step": 1250
      },
      "layer10/scale": {
        "final": 0.00465,
        "peak": 0.02614,
        "retained_pct": 17.8,
        "final_step": 1250
      },
      "layer10/attn": {
        "final": 0.01124,
        "peak": 0.12831,
        "retained_pct": 8.8,
        "final_step": 1250
      },
      "layer10/mlp": {
        "final": 0.02601,
        "peak": 0.14014,
        "retained_pct": 18.6,
        "final_step": 1250
      }
    },
    "sparse": {
      "skip": {
        "final": 0.00204,
        "peak": 0.01429,
        "retained_pct": 14.3,
        "final_step": 1250
      },
      "embedding": {
        "final": 0.02638,
        "peak": 0.38251,
        "retained_pct": 6.9,
        "final_step": 1250
      },
      "layer00/scale": {
        "final": 0.00387,
        "peak": 0.02317,
        "retained_pct": 16.7,
        "final_step": 1250
      },
      "layer00/attn": {
        "final": 0.01015,
        "peak": 0.25578,
        "retained_pct": 4.0,
        "final_step": 1250
      },
      "layer00/mlp": {
        "final": 0.01554,
        "peak": 0.34773,
        "retained_pct": 4.5,
        "final_step": 1250
      },
      "layer01/scale": {
        "final": 0.00294,
        "peak": 0.02113,
        "retained_pct": 13.9,
        "final_step": 1250
      },
      "layer01/attn": {
        "final": 0.00848,
        "peak": 0.15657,
        "retained_pct": 5.4,
        "final_step": 1250
      },
      "layer01/mlp": {
        "final": 0.01387,
        "peak": 0.15014,
        "retained_pct": 9.2,
        "final_step": 1250
      },
      "layer02/scale": {
        "final": 0.00259,
        "peak": 0.0225,
        "retained_pct": 11.5,
        "final_step": 1250
      },
      "layer02/attn": {
        "final": 0.0093,
        "peak": 0.16062,
        "retained_pct": 5.8,
        "final_step": 1250
      },
      "layer02/mlp": {
        "final": 0.01473,
        "peak": 0.16803,
        "retained_pct": 8.8,
        "final_step": 1250
      },
      "layer03/scale": {
        "final": 0.00265,
        "peak": 0.02257,
        "retained_pct": 11.7,
        "final_step": 1250
      },
      "layer03/attn": {
        "final": 0.00883,
        "peak": 0.13495,
        "retained_pct": 6.5,
        "final_step": 1250
      },
      "layer03/mlp": {
        "final": 0.01313,
        "peak": 0.13175,
        "retained_pct": 10.0,
        "final_step": 1250
      },
      "layer04/scale": {
        "final": 0.00227,
        "peak": 0.01437,
        "retained_pct": 15.8,
        "final_step": 1250
      },
      "layer04/attn": {
        "final": 0.01051,
        "peak": 0.06872,
        "retained_pct": 15.3,
        "final_step": 1250
      },
      "layer04/mlp": {
        "final": 0.01393,
        "peak": 0.10551,
        "retained_pct": 13.2,
        "final_step": 1250
      },
      "layer05/scale": {
        "final": 0.00208,
        "peak": 0.01307,
        "retained_pct": 15.9,
        "final_step": 1250
      },
      "layer05/attn": {
        "final": 0.00921,
        "peak": 0.04913,
        "retained_pct": 18.7,
        "final_step": 1250
      },
      "layer05/mlp": {
        "final": 0.01363,
        "peak": 0.07524,
        "retained_pct": 18.1,
        "final_step": 1250
      },
      "layer06/scale": {
        "final": 0.0023,
        "peak": 0.01714,
        "retained_pct": 13.4,
        "final_step": 1250
      },
      "layer06/attn": {
        "final": 0.01069,
        "peak": 0.06803,
        "retained_pct": 15.7,
        "final_step": 1250
      },
      "layer06/mlp": {
        "final": 0.01315,
        "peak": 0.07495,
        "retained_pct": 17.5,
        "final_step": 1250
      },
      "layer07/scale": {
        "final": 0.00283,
        "peak": 0.02111,
        "retained_pct": 13.4,
        "final_step": 1250
      },
      "layer07/attn": {
        "final": 0.01068,
        "peak": 0.07789,
        "retained_pct": 13.7,
        "final_step": 1250
      },
      "layer07/mlp": {
        "final": 0.01446,
        "peak": 0.0843,
        "retained_pct": 17.1,
        "final_step": 1250
      },
      "layer08/scale": {
        "final": 0.00331,
        "peak": 0.02429,
        "retained_pct": 13.6,
        "final_step": 1250
      },
      "layer08/attn": {
        "final": 0.01078,
        "peak": 0.12098,
        "retained_pct": 8.9,
        "final_step": 1250
      },
      "layer08/mlp": {
        "final": 0.01673,
        "peak": 0.10118,
        "retained_pct": 16.5,
        "final_step": 1250
      },
      "layer09/scale": {
        "final": 0.00437,
        "peak": 0.02723,
        "retained_pct": 16.1,
        "final_step": 1250
      },
      "layer09/attn": {
        "final": 0.01329,
        "peak": 0.16084,
        "retained_pct": 8.3,
        "final_step": 1250
      },
      "layer09/mlp": {
        "final": 0.01887,
        "peak": 0.12172,
        "retained_pct": 15.5,
        "final_step": 1250
      },
      "layer10/scale": {
        "final": 0.00501,
        "peak": 0.02614,
        "retained_pct": 19.2,
        "final_step": 1250
      },
      "layer10/attn": {
        "final": 0.01143,
        "peak": 0.12872,
        "retained_pct": 8.9,
        "final_step": 1250
      },
      "layer10/mlp": {
        "final": 0.02622,
        "peak": 0.14014,
        "retained_pct": 18.7,
        "final_step": 1250
      }
    },
    "dense": {
      "skip": {
        "final": 0.00115,
        "peak": 0.01429,
        "retained_pct": 8.1,
        "final_step": 1250
      },
      "embedding": {
        "final": 0.02628,
        "peak": 0.38265,
        "retained_pct": 6.9,
        "final_step": 1250
      },
      "layer00/scale": {
        "final": 0.00378,
        "peak": 0.02317,
        "retained_pct": 16.3,
        "final_step": 1250
      },
      "layer00/attn": {
        "final": 0.00995,
        "peak": 0.25578,
        "retained_pct": 3.9,
        "final_step": 1250
      },
      "layer00/mlp": {
        "final": 0.01703,
        "peak": 0.34773,
        "retained_pct": 4.9,
        "final_step": 1250
      },
      "layer01/scale": {
        "final": 0.00298,
        "peak": 0.02113,
        "retained_pct": 14.1,
        "final_step": 1250
      },
      "layer01/attn": {
        "final": 0.00963,
        "peak": 0.15657,
        "retained_pct": 6.1,
        "final_step": 1250
      },
      "layer01/mlp": {
        "final": 0.01553,
        "peak": 0.15014,
        "retained_pct": 10.3,
        "final_step": 1250
      },
      "layer02/scale": {
        "final": 0.00305,
        "peak": 0.0225,
        "retained_pct": 13.6,
        "final_step": 1250
      },
      "layer02/attn": {
        "final": 0.01104,
        "peak": 0.16062,
        "retained_pct": 6.9,
        "final_step": 1250
      },
      "layer02/mlp": {
        "final": 0.01449,
        "peak": 0.16803,
        "retained_pct": 8.6,
        "final_step": 1250
      },
      "layer03/scale": {
        "final": 0.0031,
        "peak": 0.02257,
        "retained_pct": 13.7,
        "final_step": 1250
      },
      "layer03/attn": {
        "final": 0.01206,
        "peak": 0.13495,
        "retained_pct": 8.9,
        "final_step": 1250
      },
      "layer03/mlp": {
        "final": 0.01554,
        "peak": 0.13175,
        "retained_pct": 11.8,
        "final_step": 1250
      },
      "layer04/scale": {
        "final": 0.00273,
        "peak": 0.01437,
        "retained_pct": 19.0,
        "final_step": 1250
      },
      "layer04/attn": {
        "final": 0.01077,
        "peak": 0.07047,
        "retained_pct": 15.3,
        "final_step": 1250
      },
      "layer04/mlp": {
        "final": 0.01417,
        "peak": 0.10551,
        "retained_pct": 13.4,
        "final_step": 1250
      },
      "layer05/scale": {
        "final": 0.0026,
        "peak": 0.01419,
        "retained_pct": 18.3,
        "final_step": 1250
      },
      "layer05/attn": {
        "final": 0.01086,
        "peak": 0.0584,
        "retained_pct": 18.6,
        "final_step": 1250
      },
      "layer05/mlp": {
        "final": 0.01362,
        "peak": 0.07524,
        "retained_pct": 18.1,
        "final_step": 1250
      },
      "layer06/scale": {
        "final": 0.00277,
        "peak": 0.01809,
        "retained_pct": 15.3,
        "final_step": 1250
      },
      "layer06/attn": {
        "final": 0.00918,
        "peak": 0.06803,
        "retained_pct": 13.5,
        "final_step": 1250
      },
      "layer06/mlp": {
        "final": 0.01371,
        "peak": 0.07495,
        "retained_pct": 18.3,
        "final_step": 1250
      },
      "layer07/scale": {
        "final": 0.00315,
        "peak": 0.02179,
        "retained_pct": 14.5,
        "final_step": 1250
      },
      "layer07/attn": {
        "final": 0.00847,
        "peak": 0.07789,
        "retained_pct": 10.9,
        "final_step": 1250
      },
      "layer07/mlp": {
        "final": 0.01401,
        "peak": 0.0843,
        "retained_pct": 16.6,
        "final_step": 1250
      },
      "layer08/scale": {
        "final": 0.00344,
        "peak": 0.02429,
        "retained_pct": 14.1,
        "final_step": 1250
      },
      "layer08/attn": {
        "final": 0.00981,
        "peak": 0.12098,
        "retained_pct": 8.1,
        "final_step": 1250
      },
      "layer08/mlp": {
        "final": 0.01506,
        "peak": 0.10118,
        "retained_pct": 14.9,
        "final_step": 1250
      },
      "layer09/scale": {
        "final": 0.00361,
        "peak": 0.02723,
        "retained_pct": 13.3,
        "final_step": 1250
      },
      "layer09/attn": {
        "final": 0.00813,
        "peak": 0.16084,
        "retained_pct": 5.1,
        "final_step": 1250
      },
      "layer09/mlp": {
        "final": 0.01636,
        "peak": 0.12172,
        "retained_pct": 13.4,
        "final_step": 1250
      },
      "layer10/scale": {
        "final": 0.00377,
        "peak": 0.02614,
        "retained_pct": 14.4,
        "final_step": 1250
      },
      "layer10/attn": {
        "final": 0.01251,
        "peak": 0.12872,
        "retained_pct": 9.7,
        "final_step": 1250
      },
      "layer10/mlp": {
        "final": 0.02384,
        "peak": 0.14014,
        "retained_pct": 17.0,
        "final_step": 1250
      }
    }
  },
  "gpu_profiling": {
    "no_skip": {
      "tensor_core_pct": 55.6,
      "nccl_pct": 18.9,
      "norm_pct": 10.6,
      "other_pct": 14.8,
      "total_kernel_ms": 1652.0
    },
    "sparse": {
      "tensor_core_pct": 56.4,
      "nccl_pct": 17.8,
      "norm_pct": 10.8,
      "other_pct": 15.0,
      "total_kernel_ms": 1629.0
    },
    "dense": {
      "tensor_core_pct": 54.8,
      "nccl_pct": 17.1,
      "norm_pct": 13.3,
      "other_pct": 14.7,
      "total_kernel_ms": 1664.0
    }
  },
  "training_speed": {
    "no_skip": {
      "avg_ms_per_step": 313.5,
      "total_steps": 1273,
      "tok_per_sec": 1254451
    },
    "sparse": {
      "avg_ms_per_step": 312.8,
      "total_steps": 1293,
      "tok_per_sec": 1256918
    },
    "dense": {
      "avg_ms_per_step": 314.9,
      "total_steps": 1293,
      "tok_per_sec": 1248711
    }
  },
  "summary": {
    "final_results": {
      "no_skip": "1.1922 at step 1273",
      "sparse": "1.1906 at step 1293",
      "dense": "1.1906 at step 1293"
    },
    "key_findings": [
      "Dense skips overtake sparse at step 700 and stay ahead through end of training",
      "At step 1000: dense=1.2280 vs sparse=1.2311 (+0.003 bpb improvement)",
      "Dense skips increase middle layer (3-5) gradient norms by 11% vs sparse",
      "Dense costs 3% more ms/step (320 vs 311ms) due to 30 skip ops vs 5",
      "Sparse skip connections worth +0.002 bpb vs no skips",
      "Dense skip connections worth +0.003 bpb vs sparse in late training",
      "Net effect after speed penalty: ~0.002 bpb improvement from dense over sparse"
    ],
    "gradient_valley_analysis": {
      "problem": "Middle layers 3-5 get weakest gradients in U-Net due to longest gradient path",
      "evidence": "Layer 4 gradient retained only 19-26% of peak vs layer 10 at 9-37%",
      "dense_fix": "Dense skips give middle layers direct gradient shortcuts to all decoder layers",
      "result": "Middle layer avg grad: no_skip=0.01172, sparse=0.01154, dense=0.01284 (+11%)"
    }
  }
}